{
  "task": "xml_file_upload", 
  "depends_on": [
    "completed@xml_upload_to_aws", 
    "completed@prepare_metadata_xml"
  ], 
  "tool": "upload", 
  "command": "upload.py", 
  "output": [
    {
      "_jt_": {
        "worker_id": "worker.1498852245.9031a28a.host.231181a3.10.10.1.7", 
        "workflow_version": "0.6.6", 
        "jt_version": "0.1.0rc9", 
        "task_state": "completed"
      }, 
      "runtime": {
        "task_start": 1499267008, 
        "task_stop": 1499267022
      }
    }
  ], 
  "input": {
    "file_name": "bundle.EGAR00001196888.xml", 
    "object_id": "f196750e-9b5c-5c4a-bc23-fe9209c3be1d", 
    "file_md5sum": "d47e53cf4533dac2b1c1aa7b34f8a44f", 
    "file": "/home/ubuntu/jtracker/worker.1498852245.9031a28a.host.231181a3.10.10.1.7/job.EGAR00001196888.LINC-JP.HCC150T.EGAN00001196898/task.prepare_metadata_xml/bundle.EGAR00001196888.xml", 
    "file_size": 3507, 
    "bundle_id": "EGAR00001196888"
  }, 
  "runtime": {
    "docker": null
  }
}