{
  "task": "xml_upload_to_aws", 
  "depends_on": [
    "completed@prepare_metadata_xml"
  ], 
  "tool": "upload_to_aws", 
  "command": "upload_to_aws.py", 
  "input": {
    "file_name": "bundle.EGAR00001198195.xml", 
    "object_id": "53c6fa0f-2239-5651-9f30-f25259a8cb94", 
    "file_md5sum": "ac14107ef4cff9f220ae7296c00f9521", 
    "file": "/home/ubuntu/jtracker/worker.1499714959.4f018803.host.76674056.10.10.0.19/job.EGAR00001198195.LINC-JP.HCC164T.EGAN00001196912/task.prepare_metadata_xml/bundle.EGAR00001198195.xml", 
    "file_size": 3507, 
    "bundle_id": "EGAR00001198195", 
    "project_code": "LINC-JP"
  }, 
  "runtime": {
    "docker": null
  }
}