{
  "task": "xml_file_upload", 
  "depends_on": [
    "completed@xml_upload_to_aws", 
    "completed@prepare_metadata_xml"
  ], 
  "tool": "upload", 
  "command": "upload.py", 
  "input": {
    "file_name": "bundle.EGAR00001197308.xml", 
    "object_id": "c54d8d23-d7c9-563d-8a1f-07a715a24429", 
    "file_md5sum": "{{xml_file_md5sum@prepare_metadata_xml}}", 
    "file": "{{xml_file@prepare_metadata_xml}}", 
    "file_size": "{{xml_file_size@prepare_metadata_xml}}", 
    "bundle_id": "EGAR00001197308"
  }, 
  "runtime": {
    "docker": null
  }
}