{
  "task": "xml_upload_to_aws", 
  "depends_on": [
    "completed@prepare_metadata_xml"
  ], 
  "tool": "upload_to_aws", 
  "command": "upload_to_aws.py", 
  "output": [
    {
      "task_state": "completed", 
      "idx_file_md5sum": null, 
      "idx_file": null, 
      "file_md5sum": "98989cd086809be76e410dc7aa0e4cdf", 
      "worker_id": "worker.1497977458.22c1a91d.host.231181a3.10.10.1.7", 
      "file": "/home/ubuntu/jtracker/worker.1497976629.4af50a25.host.231181a3.10.10.1.7/job.EGAR00001111555.LINC-JP.HCC28T.EGAN00001085983/task.prepare_metadata_xml/bundle.EGAR00001111555.xml", 
      "file_size": 3663, 
      "runtime": {
        "task_start": 1498037840, 
        "task_stop": 1498037851
      }
    }
  ], 
  "input": {
    "file_name": "bundle.EGAR00001111555.xml", 
    "object_id": "e5a5f744-4b2f-5464-8cca-3544c8dbd3e4", 
    "file_md5sum": "98989cd086809be76e410dc7aa0e4cdf", 
    "file": "/home/ubuntu/jtracker/worker.1497976629.4af50a25.host.231181a3.10.10.1.7/job.EGAR00001111555.LINC-JP.HCC28T.EGAN00001085983/task.prepare_metadata_xml/bundle.EGAR00001111555.xml", 
    "file_size": 3663, 
    "bundle_id": "EGAR00001111555"
  }, 
  "runtime": {
    "docker": null
  }
}