{
  "task": "xml_upload_to_aws", 
  "depends_on": [
    "completed@prepare_metadata_xml"
  ], 
  "tool": "upload_to_aws", 
  "command": "upload_to_aws.py", 
  "output": [
    {
      "task_state": "completed", 
      "idx_file_md5sum": null, 
      "idx_file": null, 
      "file_md5sum": "448e5e63858786d7bbbd49ea61939e23", 
      "worker_id": "worker.1497970867.814131d2.host.231181a3.10.10.1.7", 
      "file": "/home/ubuntu/jtracker/worker.1497976629.4af50a25.host.231181a3.10.10.1.7/job.EGAR00001111712.LINC-JP.HCC29T.EGAN00001085984/task.prepare_metadata_xml/bundle.EGAR00001111712.xml", 
      "file_size": 3665, 
      "runtime": {
        "task_start": 1497989090, 
        "task_stop": 1497989096
      }
    }
  ], 
  "input": {
    "file_name": "bundle.EGAR00001111712.xml", 
    "object_id": "af0d9bf6-7089-52fc-9223-4df072e88318", 
    "file_md5sum": "448e5e63858786d7bbbd49ea61939e23", 
    "file": "/home/ubuntu/jtracker/worker.1497976629.4af50a25.host.231181a3.10.10.1.7/job.EGAR00001111712.LINC-JP.HCC29T.EGAN00001085984/task.prepare_metadata_xml/bundle.EGAR00001111712.xml", 
    "file_size": 3665, 
    "bundle_id": "EGAR00001111712"
  }, 
  "runtime": {
    "docker": null
  }
}