{
  "task": "xml_upload_to_aws", 
  "depends_on": [
    "completed@prepare_metadata_xml"
  ], 
  "tool": "upload_to_aws", 
  "command": "upload_to_aws.py", 
  "input": {
    "file_name": "bundle.EGAR00001257757.xml", 
    "object_id": "4270c570-7a44-5cf6-b867-806752031b8c", 
    "file_md5sum": "143e263ebc861f4ef364b68444e66137", 
    "file": "/home/ubuntu/jtracker/worker.1500992412.e26ce601.host.231181a3.10.10.1.7/job.EGAR00001257757.BTCA-JP.BD67T.EGAN00001246871/task.prepare_metadata_xml/bundle.EGAR00001257757.xml", 
    "file_size": 3174, 
    "bundle_id": "EGAR00001257757", 
    "project_code": "BTCA-JP"
  }, 
  "runtime": {
    "docker": null
  }
}