{
  "task": "xml_file_upload", 
  "depends_on": [
    "completed@xml_upload_to_aws", 
    "completed@prepare_metadata_xml"
  ], 
  "tool": "upload", 
  "command": "upload.py", 
  "input": {
    "file_name": "bundle.EGAR00001196947.xml", 
    "object_id": "973aa7f6-bfa3-5825-a3c1-c6595caaa169", 
    "file_md5sum": "07d684fe4f6a2da7d79f2f6a48b921d4", 
    "file": "/home/ubuntu/jtracker/worker.1499714959.4f018803.host.76674056.10.10.0.19/job.EGAR00001196947.LINC-JP.HCC151T.EGAN00001196899/task.prepare_metadata_xml/bundle.EGAR00001196947.xml", 
    "file_size": 3505, 
    "bundle_id": "EGAR00001196947"
  }, 
  "runtime": {
    "docker": null
  }
}