{
  "task": "xml_upload_to_aws", 
  "depends_on": [
    "completed@prepare_metadata_xml"
  ], 
  "tool": "upload_to_aws", 
  "command": "upload_to_aws.py", 
  "input": {
    "file_name": "bundle.EGAR00001114790.xml", 
    "object_id": "f7cca31c-6405-5420-8a6a-ceaedcc3c2f9", 
    "file_md5sum": "5e5acfe9fe7aee3ba12f2253cce19506", 
    "file": "/home/ubuntu/jtracker/worker.1498852245.9031a28a.host.231181a3.10.10.1.7/job.EGAR00001114790.LINC-JP.HCC77T.EGAN00001086027/task.prepare_metadata_xml/bundle.EGAR00001114790.xml", 
    "file_size": 3665, 
    "bundle_id": "EGAR00001114790", 
    "project_code": "LINC-JP"
  }, 
  "runtime": {
    "docker": null
  }
}