{
  "task": "xml_upload_to_aws", 
  "depends_on": [
    "completed@prepare_metadata_xml"
  ], 
  "tool": "upload_to_aws", 
  "command": "upload_to_aws.py", 
  "output": [
    {
      "task_state": "completed", 
      "idx_file_md5sum": null, 
      "idx_file": null, 
      "file_md5sum": "3c00a940040700971ecbd437aa6441af", 
      "worker_id": "worker.1498061104.e9e1f846.host.231181a3.10.10.1.7", 
      "file": "/home/ubuntu/jtracker/worker.1498061104.e9e1f846.host.231181a3.10.10.1.7/job.EGAR00001106683.LINC-JP.BN01T.EGAN00001085929/task.prepare_metadata_xml/bundle.EGAR00001106683.xml", 
      "file_size": 3655, 
      "runtime": {
        "task_start": 1498181356, 
        "task_stop": 1498181362
      }
    }
  ], 
  "input": {
    "file_name": "bundle.EGAR00001106683.xml", 
    "object_id": "9f925814-772b-5f91-a3d3-a7be2a909d03", 
    "file_md5sum": "3c00a940040700971ecbd437aa6441af", 
    "file": "/home/ubuntu/jtracker/worker.1498061104.e9e1f846.host.231181a3.10.10.1.7/job.EGAR00001106683.LINC-JP.BN01T.EGAN00001085929/task.prepare_metadata_xml/bundle.EGAR00001106683.xml", 
    "file_size": 3655, 
    "bundle_id": "EGAR00001106683"
  }, 
  "runtime": {
    "docker": null
  }
}