{
  "task": "xml_file_upload", 
  "depends_on": [
    "completed@xml_upload_to_aws", 
    "completed@prepare_metadata_xml"
  ], 
  "tool": "upload", 
  "command": "upload.py", 
  "output": [
    {
      "runtime": {
        "task_start": 1498505854, 
        "task_stop": 1498505869
      }, 
      "worker_id": "worker.1498061579.3de84c81.host.231181a3.10.10.1.7", 
      "task_state": "completed"
    }
  ], 
  "input": {
    "file_name": "bundle.EGAR00001107772.xml", 
    "object_id": "4576a03d-d60f-5fca-a381-50b4d3b40c48", 
    "file_md5sum": "e0ad68a1038c395214203457270b7a9f", 
    "file": "/home/ubuntu/jtracker/worker.1498061597.634d02ac.host.231181a3.10.10.1.7/job.EGAR00001107772.LINC-JP.BN23T.EGAN00001085941/task.prepare_metadata_xml/bundle.EGAR00001107772.xml", 
    "file_size": 3659, 
    "bundle_id": "EGAR00001107772"
  }, 
  "runtime": {
    "docker": null
  }
}