{
  "task": "xml_file_upload", 
  "depends_on": [
    "completed@xml_upload_to_aws", 
    "completed@prepare_metadata_xml"
  ], 
  "tool": "upload", 
  "command": "upload.py", 
  "input": {
    "file_name": "bundle.EGAR00001200893.xml", 
    "object_id": "90ac0b49-482d-5bff-9cb4-bde6212ca281", 
    "file_md5sum": "e94a483b388449f66f2963e0f026317a", 
    "file": "/home/ubuntu/jtracker/worker.1498852245.9031a28a.host.231181a3.10.10.1.7/job.EGAR00001200893.LINC-JP.HCC9T.EGAN00001196872/task.prepare_metadata_xml/bundle.EGAR00001200893.xml", 
    "file_size": 3499, 
    "bundle_id": "EGAR00001200893"
  }, 
  "runtime": {
    "docker": null
  }
}