{
  "task": "xml_upload_to_aws", 
  "depends_on": [
    "completed@prepare_metadata_xml"
  ], 
  "tool": "upload_to_aws", 
  "command": "upload_to_aws.py", 
  "output": [
    {
      "task_state": "completed", 
      "idx_file_md5sum": null, 
      "idx_file": null, 
      "file_md5sum": "333613c00dd029f156d6c89f6d4bf5b9", 
      "worker_id": "worker.1498061579.3de84c81.host.231181a3.10.10.1.7", 
      "file": "/home/ubuntu/jtracker/worker.1498061579.3de84c81.host.231181a3.10.10.1.7/job.EGAR00001107496.LINC-JP.BN17T.EGAN00001085937/task.prepare_metadata_xml/bundle.EGAR00001107496.xml", 
      "file_size": 3659, 
      "runtime": {
        "task_start": 1498552089, 
        "task_stop": 1498552096
      }
    }
  ], 
  "input": {
    "file_name": "bundle.EGAR00001107496.xml", 
    "object_id": "40d7fc12-5ead-5822-9d3f-c51d24e4ea00", 
    "file_md5sum": "333613c00dd029f156d6c89f6d4bf5b9", 
    "file": "/home/ubuntu/jtracker/worker.1498061579.3de84c81.host.231181a3.10.10.1.7/job.EGAR00001107496.LINC-JP.BN17T.EGAN00001085937/task.prepare_metadata_xml/bundle.EGAR00001107496.xml", 
    "file_size": 3659, 
    "bundle_id": "EGAR00001107496"
  }, 
  "runtime": {
    "docker": null
  }
}