{
  "task": "xml_upload_to_aws", 
  "depends_on": [
    "completed@prepare_metadata_xml"
  ], 
  "tool": "upload_to_aws", 
  "command": "upload_to_aws.py", 
  "input": {
    "file_name": "bundle.EGAR00001260139.xml", 
    "object_id": "2fa12548-6fae-5688-aaf7-84aec4b7dfa3", 
    "file_md5sum": "f1b59deb4b396ba3d8c8ff5e177f48d2", 
    "file": "/home/ubuntu/jtracker/worker.1499715487.27ffcf53.host.032f1807.10.10.0.3/job.EGAR00001260139.BTCA-JP.BD133T.EGAN00001246934/task.prepare_metadata_xml/bundle.EGAR00001260139.xml", 
    "file_size": 3186, 
    "bundle_id": "EGAR00001260139", 
    "project_code": "BTCA-JP"
  }, 
  "runtime": {
    "docker": null
  }
}