{
  "task": "xml_file_upload", 
  "depends_on": [
    "completed@xml_upload_to_aws", 
    "completed@prepare_metadata_xml"
  ], 
  "tool": "upload", 
  "command": "upload.py", 
  "input": {
    "file_name": "bundle.EGAR00001257726.xml", 
    "object_id": "cd094a9a-9953-534d-aa80-081ed4c315ad", 
    "file_md5sum": "eea4ac78efe21e13a7bca273a7486190", 
    "file": "/home/ubuntu/jtracker/worker.1499715487.27ffcf53.host.032f1807.10.10.0.3/job.EGAR00001257726.BTCA-JP.BD66T.EGAN00001246870/task.prepare_metadata_xml/bundle.EGAR00001257726.xml", 
    "file_size": 3174, 
    "bundle_id": "EGAR00001257726"
  }, 
  "runtime": {
    "docker": null
  }
}