{
  "task": "xml_file_upload", 
  "depends_on": [
    "completed@xml_upload_to_aws", 
    "completed@prepare_metadata_xml"
  ], 
  "tool": "upload", 
  "command": "upload.py", 
  "output": [
    {
      "_jt_": {
        "worker_id": "worker.1499714959.4f018803.host.76674056.10.10.0.19", 
        "workflow_version": "0.6.7", 
        "jt_version": "0.1.0rc9", 
        "task_state": "completed"
      }, 
      "runtime": {
        "task_start": 1501362463, 
        "task_stop": 1501362479
      }
    }
  ], 
  "input": {
    "file_name": "bundle.EGAR00001260700.xml", 
    "object_id": "8d2d1474-565b-5677-a09a-926c2d6eb820", 
    "file_md5sum": "ba1eaecfd38e7905dcc451ceb354d806", 
    "file": "/home/ubuntu/jtracker/worker.1499714959.4f018803.host.76674056.10.10.0.19/job.EGAR00001260700.BTCA-JP.BD150T.EGAN00001246950/task.prepare_metadata_xml/bundle.EGAR00001260700.xml", 
    "file_size": 3184, 
    "bundle_id": "EGAR00001260700"
  }, 
  "runtime": {
    "docker": null
  }
}