{
  "task": "xml_file_upload", 
  "depends_on": [
    "completed@xml_upload_to_aws", 
    "completed@prepare_metadata_xml"
  ], 
  "tool": "upload", 
  "command": "upload.py", 
  "output": [
    {
      "runtime": {
        "task_start": 1498514573, 
        "task_stop": 1498514587
      }, 
      "worker_id": "worker.1498061579.3de84c81.host.231181a3.10.10.1.7", 
      "task_state": "completed"
    }
  ], 
  "input": {
    "file_name": "bundle.EGAR00001107990.xml", 
    "object_id": "4e45bb4a-03ee-5731-8dab-6e2e00a4c9ed", 
    "file_md5sum": "be616df9c3d89ebcf50cfeae246e66f6", 
    "file": "/home/ubuntu/jtracker/worker.1498061104.e9e1f846.host.231181a3.10.10.1.7/job.EGAR00001107990.LINC-JP.BN26T.EGAN00001085943/task.prepare_metadata_xml/bundle.EGAR00001107990.xml", 
    "file_size": 3661, 
    "bundle_id": "EGAR00001107990"
  }, 
  "runtime": {
    "docker": null
  }
}