{
  "task": "xml_upload_to_aws", 
  "depends_on": [
    "completed@prepare_metadata_xml"
  ], 
  "tool": "upload_to_aws", 
  "command": "upload_to_aws.py", 
  "input": {
    "file_name": "bundle.EGAR00001257011.xml", 
    "object_id": "d97b5e65-c008-5f30-9f1d-5b784b7634e0", 
    "file_md5sum": "f732848de56978c1fbf94d639eb65c99", 
    "file": "/home/ubuntu/jtracker/worker.1499714959.4f018803.host.76674056.10.10.0.19/job.EGAR00001257011.BTCA-JP.BD47T.EGAN00001246851/task.prepare_metadata_xml/bundle.EGAR00001257011.xml", 
    "file_size": 3176, 
    "bundle_id": "EGAR00001257011", 
    "project_code": "BTCA-JP"
  }, 
  "runtime": {
    "docker": null
  }
}