{
  "task": "xml_file_upload", 
  "depends_on": [
    "completed@xml_upload_to_aws", 
    "completed@prepare_metadata_xml"
  ], 
  "tool": "upload", 
  "command": "upload.py", 
  "output": [
    {
      "_jt_": {
        "worker_id": "worker.1499714959.4f018803.host.76674056.10.10.0.19", 
        "workflow_version": "0.6.7", 
        "jt_version": "0.1.0rc9", 
        "task_state": "completed"
      }, 
      "runtime": {
        "task_start": 1499839325, 
        "task_stop": 1499839339
      }
    }
  ], 
  "input": {
    "file_name": "bundle.EGAR00001196828.xml", 
    "object_id": "3b882b47-498d-546b-8c36-43c51d67cd81", 
    "file_md5sum": "7581f2911ad8fe1f99a8cc91eed0f7fc", 
    "file": "/home/ubuntu/jtracker/worker.1499714959.4f018803.host.76674056.10.10.0.19/job.EGAR00001196828.LINC-JP.HCC150T.EGAN00001196898/task.prepare_metadata_xml/bundle.EGAR00001196828.xml", 
    "file_size": 3501, 
    "bundle_id": "EGAR00001196828"
  }, 
  "runtime": {
    "docker": null
  }
}