{
  "task": "xml_upload_to_aws", 
  "depends_on": [
    "completed@prepare_metadata_xml"
  ], 
  "tool": "upload_to_aws", 
  "command": "upload_to_aws.py", 
  "input": {
    "file_name": "bundle.EGAR00001197883.xml", 
    "object_id": "1e3c390c-430f-54ad-ad9e-f2d2fc97a04c", 
    "file_md5sum": "f8d241b83a32c943be8a49f07bfb82eb", 
    "file": "/home/ubuntu/jtracker/worker.1499714959.4f018803.host.76674056.10.10.0.19/job.EGAR00001197883.LINC-JP.HCC160T.EGAN00001196908/task.prepare_metadata_xml/bundle.EGAR00001197883.xml", 
    "file_size": 3507, 
    "bundle_id": "EGAR00001197883", 
    "project_code": "LINC-JP"
  }, 
  "runtime": {
    "docker": null
  }
}