{
  "task": "xml_file_upload", 
  "depends_on": [
    "completed@xml_upload_to_aws", 
    "completed@prepare_metadata_xml"
  ], 
  "tool": "upload", 
  "command": "upload.py", 
  "input": {
    "file_name": "bundle.EGAR00001200563.xml", 
    "object_id": "61c07951-ff90-56ce-bc5d-25fb5e03f015", 
    "file_md5sum": "f90f55b701b9cd023ff00f817ea7309d", 
    "file": "/home/ubuntu/jtracker/worker.1498852245.9031a28a.host.231181a3.10.10.1.7/job.EGAR00001200563.LINC-JP.HCC99T.EGAN00001196883/task.prepare_metadata_xml/bundle.EGAR00001200563.xml", 
    "file_size": 3501, 
    "bundle_id": "EGAR00001200563"
  }, 
  "runtime": {
    "docker": null
  }
}