{
  "task": "xml_upload_to_aws", 
  "depends_on": [
    "completed@prepare_metadata_xml"
  ], 
  "tool": "upload_to_aws", 
  "command": "upload_to_aws.py", 
  "output": [
    {
      "idx_file_size": 0, 
      "idx_file_md5sum": null, 
      "_jt_": {
        "worker_id": "worker.1498852245.9031a28a.host.231181a3.10.10.1.7", 
        "workflow_version": "0.6.6", 
        "jt_version": "0.1.0rc9", 
        "task_state": "completed"
      }, 
      "idx_file": null, 
      "allowed_upload": true, 
      "file_md5sum": "1d7d907e46175bc75a282a985dbc559c", 
      "file": "/home/ubuntu/jtracker/worker.1498852245.9031a28a.host.231181a3.10.10.1.7/job.EGAR00001200627.LINC-JP.HCC99T.EGAN00001196883/task.prepare_metadata_xml/bundle.EGAR00001200627.xml", 
      "file_size": 3505, 
      "runtime": {
        "task_start": 1498908368, 
        "task_stop": 1498908374
      }
    }
  ], 
  "input": {
    "file_name": "bundle.EGAR00001200627.xml", 
    "object_id": "42fd2e8c-ebde-57f0-afff-4d89fbecb695", 
    "file_md5sum": "1d7d907e46175bc75a282a985dbc559c", 
    "file": "/home/ubuntu/jtracker/worker.1498852245.9031a28a.host.231181a3.10.10.1.7/job.EGAR00001200627.LINC-JP.HCC99T.EGAN00001196883/task.prepare_metadata_xml/bundle.EGAR00001200627.xml", 
    "file_size": 3505, 
    "bundle_id": "EGAR00001200627", 
    "project_code": "LINC-JP"
  }, 
  "runtime": {
    "docker": null
  }
}