{
  "task": "xml_file_upload", 
  "depends_on": [
    "completed@xml_upload_to_aws", 
    "completed@prepare_metadata_xml"
  ], 
  "tool": "upload", 
  "command": "upload.py", 
  "input": {
    "file_name": "bundle.EGAR00001257235.xml", 
    "object_id": "1835df15-b730-55a8-8ecc-25c81e1ba78c", 
    "file_md5sum": "20f8a48950e026c43be59ff7d85c7ddd", 
    "file": "/home/ubuntu/jtracker/worker.1501683941.8334ef7e.host.76674056.10.10.0.19/job.EGAR00001257235.BTCA-JP.BD53T.EGAN00001246857/task.prepare_metadata_xml/bundle.EGAR00001257235.xml", 
    "file_size": 3176, 
    "bundle_id": "EGAR00001257235"
  }, 
  "runtime": {
    "docker": null
  }
}