{
  "task": "xml_file_upload", 
  "depends_on": [
    "completed@xml_upload_to_aws", 
    "completed@prepare_metadata_xml"
  ], 
  "tool": "upload", 
  "command": "upload.py", 
  "output": [
    {
      "_jt_": {
        "worker_id": "worker.1502296994.7b7cf9f9.host.76674056.10.10.0.19", 
        "workflow_version": "0.6.7", 
        "jt_version": "0.1.0rc9", 
        "task_state": "completed"
      }, 
      "runtime": {
        "task_start": 1502763853, 
        "task_stop": 1502763869
      }
    }
  ], 
  "input": {
    "file_name": "bundle.EGAR00001013240.xml", 
    "object_id": "4191cfcd-c0bd-5f56-8fbf-b008e78a353a", 
    "file_md5sum": "34c802886ceffbda0f5f410c433461ea", 
    "file": "/home/ubuntu/jtracker/worker.1502296994.7b7cf9f9.host.76674056.10.10.0.19/job.EGAR00001013240.BRCA-UK.PD3984a.EGAN00001000678/task.prepare_metadata_xml/bundle.EGAR00001013240.xml", 
    "file_size": 4067, 
    "bundle_id": "EGAR00001013240"
  }, 
  "runtime": {
    "docker": null
  }
}