{
  "task": "xml_upload_to_aws", 
  "depends_on": [
    "completed@prepare_metadata_xml"
  ], 
  "tool": "upload_to_aws", 
  "command": "upload_to_aws.py", 
  "output": [
    {
      "task_state": "completed", 
      "idx_file_md5sum": null, 
      "idx_file": null, 
      "file_md5sum": "fd1b1f5e6a71cc9a612147b218f7a475", 
      "worker_id": "worker.1498061597.634d02ac.host.231181a3.10.10.1.7", 
      "file": "/home/ubuntu/jtracker/worker.1498061597.634d02ac.host.231181a3.10.10.1.7/job.EGAR00001107428.LINC-JP.BN17T.EGAN00001085937/task.prepare_metadata_xml/bundle.EGAR00001107428.xml", 
      "file_size": 3655, 
      "runtime": {
        "task_start": 1498572360, 
        "task_stop": 1498572365
      }
    }
  ], 
  "input": {
    "file_name": "bundle.EGAR00001107428.xml", 
    "object_id": "7f313a07-377f-5add-8435-f0cda86286ea", 
    "file_md5sum": "fd1b1f5e6a71cc9a612147b218f7a475", 
    "file": "/home/ubuntu/jtracker/worker.1498061597.634d02ac.host.231181a3.10.10.1.7/job.EGAR00001107428.LINC-JP.BN17T.EGAN00001085937/task.prepare_metadata_xml/bundle.EGAR00001107428.xml", 
    "file_size": 3655, 
    "bundle_id": "EGAR00001107428"
  }, 
  "runtime": {
    "docker": null
  }
}