{
  "task": "xml_file_upload", 
  "depends_on": [
    "completed@xml_upload_to_aws", 
    "completed@prepare_metadata_xml"
  ], 
  "tool": "upload", 
  "command": "upload.py", 
  "input": {
    "file_name": "bundle.EGAR00001254708.xml", 
    "object_id": "ad5283c2-465c-5af2-8645-ace861fe8137", 
    "file_md5sum": "0c4c784ac42dc2f3ba35d6eee6794852", 
    "file": "/home/ubuntu/jtracker/worker.1499714959.4f018803.host.76674056.10.10.0.19/job.EGAR00001254708.BTCA-JP.BD2T.EGAN00001246807/task.prepare_metadata_xml/bundle.EGAR00001254708.xml", 
    "file_size": 3164, 
    "bundle_id": "EGAR00001254708"
  }, 
  "runtime": {
    "docker": null
  }
}