{
  "task": "xml_upload_to_aws", 
  "depends_on": [
    "completed@prepare_metadata_xml"
  ], 
  "tool": "upload_to_aws", 
  "command": "upload_to_aws.py", 
  "output": [
    {
      "task_state": "completed", 
      "idx_file_md5sum": null, 
      "idx_file": null, 
      "file_md5sum": "a9e6f0c20cecb9aac7cbe482b29a5248", 
      "worker_id": "worker.1498704651.5de27785.host.231181a3.10.10.1.7", 
      "file": "/home/ubuntu/jtracker/worker.1498719581.80520eab.host.231181a3.10.10.1.7/job.EGAR00001200768.LINC-JP.HCC99T.EGAN00001196883/task.prepare_metadata_xml/bundle.EGAR00001200768.xml", 
      "file_size": 3507, 
      "runtime": {
        "task_start": 1498738277, 
        "task_stop": 1498738289
      }
    }
  ], 
  "input": {
    "file_name": "bundle.EGAR00001200768.xml", 
    "object_id": "5ffd96e0-7806-5ece-94ca-fd1f030e646a", 
    "file_md5sum": "a9e6f0c20cecb9aac7cbe482b29a5248", 
    "file": "/home/ubuntu/jtracker/worker.1498719581.80520eab.host.231181a3.10.10.1.7/job.EGAR00001200768.LINC-JP.HCC99T.EGAN00001196883/task.prepare_metadata_xml/bundle.EGAR00001200768.xml", 
    "file_size": 3507, 
    "bundle_id": "EGAR00001200768"
  }, 
  "runtime": {
    "docker": null
  }
}