{
  "task": "xml_file_upload", 
  "depends_on": [
    "completed@xml_upload_to_aws", 
    "completed@prepare_metadata_xml"
  ], 
  "tool": "upload", 
  "command": "upload.py", 
  "output": [
    {
      "runtime": {
        "task_start": 1498092190, 
        "task_stop": 1498092206
      }, 
      "worker_id": "worker.1498061104.e9e1f846.host.231181a3.10.10.1.7", 
      "task_state": "completed"
    }
  ], 
  "input": {
    "file_name": "bundle.EGAR00001111060.xml", 
    "object_id": "51479c8f-c281-5f78-a8ed-9db78b71c3e5", 
    "file_md5sum": "da7e5fa1231800c80ddd83ee0c43c3cc", 
    "file": "/home/ubuntu/jtracker/worker.1498061597.634d02ac.host.231181a3.10.10.1.7/job.EGAR00001111060.LINC-JP.HCC20T.EGAN00001085977/task.prepare_metadata_xml/bundle.EGAR00001111060.xml", 
    "file_size": 3665, 
    "bundle_id": "EGAR00001111060"
  }, 
  "runtime": {
    "docker": null
  }
}