{
  "task": "xml_upload_to_aws", 
  "depends_on": [
    "completed@prepare_metadata_xml"
  ], 
  "tool": "upload_to_aws", 
  "command": "upload_to_aws.py", 
  "output": [
    {
      "task_state": "completed", 
      "idx_file_md5sum": null, 
      "idx_file": null, 
      "file_md5sum": "d96f0e449f99c6e50ab54a9e9e676053", 
      "worker_id": "worker.1497647576.02547e75.host.231181a3.10.10.1.7", 
      "file": "/home/ubuntu/jtracker/worker.1497647576.02547e75.host.231181a3.10.10.1.7/job.EGAR00001194260.LINC-JP.CCC1T.EGAN00001196923/task.prepare_metadata_xml/bundle.EGAR00001194260.xml", 
      "file_size": 3503, 
      "runtime": {
        "task_start": 1497680054, 
        "task_stop": 1497680061
      }
    }
  ], 
  "input": {
    "file_name": "bundle.EGAR00001194260.xml", 
    "object_id": "42ba70bc-182f-50af-b1e3-8bb3b50b9b58", 
    "file_md5sum": "d96f0e449f99c6e50ab54a9e9e676053", 
    "file": "/home/ubuntu/jtracker/worker.1497647576.02547e75.host.231181a3.10.10.1.7/job.EGAR00001194260.LINC-JP.CCC1T.EGAN00001196923/task.prepare_metadata_xml/bundle.EGAR00001194260.xml", 
    "file_size": 3503, 
    "bundle_id": "EGAR00001194260"
  }, 
  "runtime": {
    "docker": null
  }
}