{
  "task": "xml_file_upload", 
  "depends_on": [
    "completed@xml_upload_to_aws", 
    "completed@prepare_metadata_xml"
  ], 
  "tool": "upload", 
  "command": "upload.py", 
  "input": {
    "file_name": "bundle.EGAR00001260036.xml", 
    "object_id": "6e2364db-d23a-5d9e-9738-433306409865", 
    "file_md5sum": "06f9f59d48baceaa09fa65d0940cdde4", 
    "file": "/home/ubuntu/jtracker/worker.1500992412.e26ce601.host.231181a3.10.10.1.7/job.EGAR00001260036.BTCA-JP.BD130T.EGAN00001246931/task.prepare_metadata_xml/bundle.EGAR00001260036.xml", 
    "file_size": 3186, 
    "bundle_id": "EGAR00001260036"
  }, 
  "runtime": {
    "docker": null
  }
}