{
  "task": "xml_file_upload", 
  "depends_on": [
    "completed@xml_upload_to_aws", 
    "completed@prepare_metadata_xml"
  ], 
  "tool": "upload", 
  "command": "upload.py", 
  "output": [
    {
      "runtime": {
        "task_start": 1498483738, 
        "task_stop": 1498483760
      }, 
      "worker_id": "worker.1498061104.e9e1f846.host.231181a3.10.10.1.7", 
      "task_state": "completed"
    }
  ], 
  "input": {
    "file_name": "bundle.EGAR00001107722.xml", 
    "object_id": "379c74c5-c635-5a00-83d1-e5d87f7d41c7", 
    "file_md5sum": "2dc5fa0e4c1309c83bd6afcba4354ca5", 
    "file": "/home/ubuntu/jtracker/worker.1498061473.7ea0bb47.host.231181a3.10.10.1.7/job.EGAR00001107722.LINC-JP.BN22T.EGAN00001085940/task.prepare_metadata_xml/bundle.EGAR00001107722.xml", 
    "file_size": 3659, 
    "bundle_id": "EGAR00001107722"
  }, 
  "runtime": {
    "docker": null
  }
}