{
  "task": "xml_file_upload", 
  "depends_on": [
    "completed@xml_upload_to_aws", 
    "completed@prepare_metadata_xml"
  ], 
  "tool": "upload", 
  "command": "upload.py", 
  "output": [
    {
      "_jt_": {
        "worker_id": "worker.1500992412.e26ce601.host.231181a3.10.10.1.7", 
        "workflow_version": "0.6.7", 
        "jt_version": "0.1.0rc9", 
        "task_state": "completed"
      }, 
      "runtime": {
        "task_start": 1501215937, 
        "task_stop": 1501215957
      }
    }
  ], 
  "input": {
    "file_name": "bundle.EGAR00001257001.xml", 
    "object_id": "e4fcf2fc-cce9-5fe9-8828-005fc47b7c8a", 
    "file_md5sum": "6bec06c28419af045eaae5a2e865dd4b", 
    "file": "/home/ubuntu/jtracker/worker.1500992412.e26ce601.host.231181a3.10.10.1.7/job.EGAR00001257001.BTCA-JP.BD47T.EGAN00001246851/task.prepare_metadata_xml/bundle.EGAR00001257001.xml", 
    "file_size": 3176, 
    "bundle_id": "EGAR00001257001"
  }, 
  "runtime": {
    "docker": null
  }
}