{
  "task": "xml_upload_to_aws", 
  "depends_on": [
    "completed@prepare_metadata_xml"
  ], 
  "tool": "upload_to_aws", 
  "command": "upload_to_aws.py", 
  "input": {
    "file_name": "bundle.EGAR00001197550.xml", 
    "object_id": "947208f4-3c97-5048-8572-8676ea455f21", 
    "file_md5sum": "9552fe82a667db7be5131d7bc21aebc9", 
    "file": "/home/ubuntu/jtracker/worker.1499715487.27ffcf53.host.032f1807.10.10.0.3/job.EGAR00001197550.LINC-JP.HCC157T.EGAN00001196905/task.prepare_metadata_xml/bundle.EGAR00001197550.xml", 
    "file_size": 3507, 
    "bundle_id": "EGAR00001197550", 
    "project_code": "LINC-JP"
  }, 
  "runtime": {
    "docker": null
  }
}