{
  "task": "xml_upload_to_aws", 
  "depends_on": [
    "completed@prepare_metadata_xml"
  ], 
  "tool": "upload_to_aws", 
  "command": "upload_to_aws.py", 
  "output": [
    {
      "task_state": "completed", 
      "idx_file_md5sum": null, 
      "idx_file": null, 
      "file_md5sum": "2400b839708a8857a29d465864fb3160", 
      "worker_id": "worker.1497976629.4af50a25.host.231181a3.10.10.1.7", 
      "file": "/home/ubuntu/jtracker/worker.1497970867.814131d2.host.231181a3.10.10.1.7/job.EGAR00001111745.LINC-JP.HCC29T.EGAN00001085984/task.prepare_metadata_xml/bundle.EGAR00001111745.xml", 
      "file_size": 3667, 
      "runtime": {
        "task_start": 1498011355, 
        "task_stop": 1498011361
      }
    }
  ], 
  "input": {
    "file_name": "bundle.EGAR00001111745.xml", 
    "object_id": "6a1926cb-8f40-5cba-b153-5be0dfbe6dc8", 
    "file_md5sum": "2400b839708a8857a29d465864fb3160", 
    "file": "/home/ubuntu/jtracker/worker.1497970867.814131d2.host.231181a3.10.10.1.7/job.EGAR00001111745.LINC-JP.HCC29T.EGAN00001085984/task.prepare_metadata_xml/bundle.EGAR00001111745.xml", 
    "file_size": 3667, 
    "bundle_id": "EGAR00001111745"
  }, 
  "runtime": {
    "docker": null
  }
}