{
  "task": "xml_upload_to_aws", 
  "depends_on": [
    "completed@prepare_metadata_xml"
  ], 
  "tool": "upload_to_aws", 
  "command": "upload_to_aws.py", 
  "output": [
    {
      "idx_file_size": 0, 
      "idx_file_md5sum": null, 
      "_jt_": {
        "worker_id": "worker.1499714959.4f018803.host.76674056.10.10.0.19", 
        "workflow_version": "0.6.7", 
        "jt_version": "0.1.0rc9", 
        "task_state": "completed"
      }, 
      "idx_file": null, 
      "allowed_upload": false, 
      "file_md5sum": "ed68f6b41fef0b6e11d05e5b39fc39cf", 
      "file": "/home/ubuntu/jtracker/worker.1499714959.4f018803.host.76674056.10.10.0.19/job.EGAR00001254974.BTCA-JP.BD5T.EGAN00001246810/task.prepare_metadata_xml/bundle.EGAR00001254974.xml", 
      "file_size": 0, 
      "runtime": {
        "task_start": 1500777838, 
        "task_stop": 1500777838
      }
    }
  ], 
  "input": {
    "file_name": "bundle.EGAR00001254974.xml", 
    "object_id": "c6341e25-39f1-582c-87a8-798d40a00861", 
    "file_md5sum": "ed68f6b41fef0b6e11d05e5b39fc39cf", 
    "file": "/home/ubuntu/jtracker/worker.1499714959.4f018803.host.76674056.10.10.0.19/job.EGAR00001254974.BTCA-JP.BD5T.EGAN00001246810/task.prepare_metadata_xml/bundle.EGAR00001254974.xml", 
    "file_size": 3164, 
    "bundle_id": "EGAR00001254974", 
    "project_code": "BTCA-JP"
  }, 
  "runtime": {
    "docker": null
  }
}